ai/backend/wsproxy/VERSION
ai/backend/wsproxy/__init__.py
ai/backend/wsproxy/config.py
ai/backend/wsproxy/defs.py
ai/backend/wsproxy/exceptions.py
ai/backend/wsproxy/openapi.py
ai/backend/wsproxy/registry.py
ai/backend/wsproxy/server.py
ai/backend/wsproxy/types.py
ai/backend/wsproxy/utils.py
ai/backend/wsproxy/api/circuit.py
ai/backend/wsproxy/api/conf.py
ai/backend/wsproxy/api/endpoint.py
ai/backend/wsproxy/api/proxy.py
ai/backend/wsproxy/api/setup.py
ai/backend/wsproxy/api/types.py
ai/backend/wsproxy/api/utils.py
ai/backend/wsproxy/cli/__main__.py
ai/backend/wsproxy/cli/context.py
ai/backend/wsproxy/proxy/backend/__init__.py
ai/backend/wsproxy/proxy/backend/abc.py
ai/backend/wsproxy/proxy/backend/http.py
ai/backend/wsproxy/proxy/backend/tcp.py
ai/backend/wsproxy/proxy/frontend/__init__.py
ai/backend/wsproxy/proxy/frontend/abc.py
ai/backend/wsproxy/proxy/frontend/tcp.py
ai/backend/wsproxy/proxy/frontend/http/abc.py
ai/backend/wsproxy/proxy/frontend/http/port.py
ai/backend/wsproxy/templates/__init__.py
ai/backend/wsproxy/templates/error.jinja2
backend_ai_wsproxy-25.12.1.dist-info/METADATA
backend_ai_wsproxy-25.12.1.dist-info/WHEEL
backend_ai_wsproxy-25.12.1.dist-info/entry_points.txt
backend_ai_wsproxy-25.12.1.dist-info/namespace_packages.txt
backend_ai_wsproxy-25.12.1.dist-info/top_level.txt
backend_ai_wsproxy-25.12.1.dist-info/RECORD
